odoo/addons/project_stock_portal/README.rst
odoo/addons/project_stock_portal/__init__.py
odoo/addons/project_stock_portal/__manifest__.py
odoo/addons/project_stock_portal/i18n/es.po
odoo/addons/project_stock_portal/static/description/icon.png
odoo/addons/project_stock_portal/views/project_portal_templates.xml
odoo_addon_project_stock_portal-16.0.1.0.0.3.dist-info/METADATA
odoo_addon_project_stock_portal-16.0.1.0.0.3.dist-info/WHEEL
odoo_addon_project_stock_portal-16.0.1.0.0.3.dist-info/top_level.txt
odoo_addon_project_stock_portal-16.0.1.0.0.3.dist-info/RECORD
